mock_requests/__init__.py
mock_requests/mock_requests.py
mock_requests/data/rc_02ceb92dd75953a1b616d617.json
mock_requests/data/rc_034ccb2439183da0690c566a.json
mock_requests/data/rc_056a87586c578b8ebd2a06f7.json
mock_requests/data/rc_07c52a732ec479cc4451862f.json
mock_requests/data/rc_08b26c6c3f5119f70eba68c5.json
mock_requests/data/rc_0ad30c37060e33ee298c77dc.json
mock_requests/data/rc_0f5cb455975ee7dd8bf1cd0c.json
mock_requests/data/rc_26b1b3c112897a29ac66eb65.json
mock_requests/data/rc_309cb9fddc9796e8430d4a0a.json
mock_requests/data/rc_4004a7af8bf99a628e34caf7.json
mock_requests/data/rc_4e81791b922ffdf6d4bb91a2.json
mock_requests/data/rc_563f9d898c8b090b0fe799d6.json
mock_requests/data/rc_5c69cdc9dddf982028295264.json
mock_requests/data/rc_62b468f71fcd0271a0d48719.json
mock_requests/data/rc_8247135adf5b4dcad0d817e2.json
mock_requests/data/rc_88d73cc833ceac8335eb40fa.json
mock_requests/data/rc_8c29028ad2f427862d1d0c5b.json
mock_requests/data/rc_8d8f28ea5dca9f93bf4cd368.json
mock_requests/data/rc_8dc25febf88a3c991f0d7180.json
mock_requests/data/rc_957861b816b7a0997bf7d059.json
mock_requests/data/rc_999ed27f2ff4dedbe1d0c4b8.json
mock_requests/data/rc_a412381c13094d2196216b9d.json
mock_requests/data/rc_b9b87e45bf1a81fabb6add4b.json
mock_requests/data/rc_b9ec39371b4f8bbbddc4235f.json
mock_requests/data/rc_bc9d7b4d40c7a74d0592ff8d.json
mock_requests/data/rc_bce3501839a96c3de2f63fcd.json
mock_requests/data/rc_c13ef005391910b44e4a4c47.json
mock_requests/data/rc_d0801499d142e57e7fca7d5b.json
mock_requests/data/rc_d3cabf566f80c9a37b4499b0.json
mock_requests/data/rc_d42b3a4cfc1a949c6d4c1587.json
mock_requests/data/rc_d6a161df1ca631ed1168ddb8.json
mock_requests/data/rc_d79ebd25b437deb15276cf6b.json
mock_requests/data/rc_da425c5bd8b0597f5151bbb7.json
mock_requests/data/rc_e78914edf05d9129945d48f6.json
mock_requests/data/rc_e7f268ae13f5a87a3a5878ff.json
mock_requests/data/rc_ee5f5500f3ebe0d9490b3095.json
mock_requests/data/rc_fbc72d677780e30c38f46001.json
mock_requests_restcountries-0.7.0.dist-info/licenses/LICENSE
mock_requests_restcountries-0.7.0.dist-info/METADATA
mock_requests_restcountries-0.7.0.dist-info/WHEEL
mock_requests_restcountries-0.7.0.dist-info/top_level.txt
mock_requests_restcountries-0.7.0.dist-info/RECORD
