Metadata-Version: 2.4
Name: mock-requests-restcountries
Version: 0.7.0
Summary: REST Countries mock requests: pre-cached per-URL; missing URLs fetched and cached automatically.
Home-page: https://pypi.org/project/mock-requests-restcountries/
Author: Ethan Steinfeld
License: MIT
Classifier: Programming Language :: Python :: 3
Classifier: License :: OSI Approved :: MIT License
Classifier: Intended Audience :: Developers
Classifier: Topic :: Software Development :: Testing
Classifier: Topic :: Internet :: WWW/HTTP
Requires-Python: >=3.8
License-File: LICENSE
Requires-Dist: requests
Provides-Extra: dev
Requires-Dist: build; extra == "dev"
Dynamic: license-file
